activeview/__init__.py
activeview/apps.py
activeview/models.py
activeview/urls.py
activeview/views.py
activeview/templatetags/__init__.py
activeview/templatetags/activeview.py
django_activeview-0.1.3.dist-info/DESCRIPTION.rst
django_activeview-0.1.3.dist-info/METADATA
django_activeview-0.1.3.dist-info/RECORD
django_activeview-0.1.3.dist-info/WHEEL
django_activeview-0.1.3.dist-info/metadata.json
django_activeview-0.1.3.dist-info/top_level.txt
django_activeview-0.1.3.dist-info/zip-safe
